voicecontrolx/__init__.py
voicecontrolx/actions.py
voicecontrolx/core.py
voicecontrolx_raj-0.1.1.dist-info/licenses/LICENSE
voicecontrolx_raj-0.1.1.dist-info/METADATA
voicecontrolx_raj-0.1.1.dist-info/WHEEL
voicecontrolx_raj-0.1.1.dist-info/entry_points.txt
voicecontrolx_raj-0.1.1.dist-info/top_level.txt
voicecontrolx_raj-0.1.1.dist-info/RECORD
