Metadata-Version: 2.4
Name: voicecontrolx-raj
Version: 0.1.1
Summary: Offline Windows voice assistant in Python
Home-page: https://github.com/TRajalingam/voicecontrolx-raj
Author: RAJALINGAMT
Author-email: raju031001@gmail.com
Classifier: Programming Language :: Python :: 3
Classifier: Operating System :: Microsoft :: Windows
Classifier: License :: OSI Approved :: MIT License
License-File: LICENSE
Requires-Dist: SpeechRecognition
Requires-Dist: pyttsx3
Requires-Dist: pyaudio
Requires-Dist: pyautogui
Requires-Dist: vosk
Requires-Dist: sounddevice
Dynamic: author
Dynamic: author-email
Dynamic: classifier
Dynamic: description
Dynamic: description-content-type
Dynamic: home-page
Dynamic: license-file
Dynamic: requires-dist
Dynamic: summary
